procnet/__init__.py
procnet-0.0.1.dist-info/LICENSE
procnet-0.0.1.dist-info/METADATA
procnet-0.0.1.dist-info/WHEEL
procnet-0.0.1.dist-info/top_level.txt
procnet-0.0.1.dist-info/RECORD
