Metadata-Version: 2.1
Name: procnet
Version: 0.0.1
Summary: Distributed Processing Network with DiSwarm
Home-page: https://github.com/iTecAI/ProcNet
Author: iTecX
Author-email: matteovh@gmail.com
License: UNKNOWN
Platform: UNKNOWN
Classifier: Programming Language :: Python :: 3
Classifier: License :: OSI Approved :: MIT License
Classifier: Operating System :: OS Independent
Requires-Dist: diswarm-handler
